BidanyiXiadeYouhuoshu/README.md
BidanyiXiadeYouhuoshu/__init__.py
BidanyiXiadeYouhuoshu/__main__.py
BidanyiXiadeYouhuoshu/file.epub
BidanyiXiadeYouhuoshu/index.html
BidanyiXiadeYouhuoshu/css/__init__.py
BidanyiXiadeYouhuoshu/css/annotations.css
BidanyiXiadeYouhuoshu/css/main.css
BidanyiXiadeYouhuoshu/css/normalize.css
BidanyiXiadeYouhuoshu/css/popup.css
BidanyiXiadeYouhuoshu/font/__init__.py
BidanyiXiadeYouhuoshu/font/fontello.eot
BidanyiXiadeYouhuoshu/font/fontello.svg
BidanyiXiadeYouhuoshu/font/fontello.ttf
BidanyiXiadeYouhuoshu/font/fontello.woff
BidanyiXiadeYouhuoshu/img/__init__.py
BidanyiXiadeYouhuoshu/img/annotator-glyph-sprite.png
BidanyiXiadeYouhuoshu/img/annotator-icon-sprite.png
BidanyiXiadeYouhuoshu/img/apple-touch-icon.png
BidanyiXiadeYouhuoshu/img/cancelfullscreen.png
BidanyiXiadeYouhuoshu/img/close.png
BidanyiXiadeYouhuoshu/img/fullscreen.png
BidanyiXiadeYouhuoshu/img/loader.gif
BidanyiXiadeYouhuoshu/img/menu-icon.png
BidanyiXiadeYouhuoshu/img/save.png
BidanyiXiadeYouhuoshu/img/saved.png
BidanyiXiadeYouhuoshu/img/settings-s.png
BidanyiXiadeYouhuoshu/img/settings.png
BidanyiXiadeYouhuoshu/img/star.png
BidanyiXiadeYouhuoshu/js/__init__.py
BidanyiXiadeYouhuoshu/js/epub.js
BidanyiXiadeYouhuoshu/js/epub.min.js
BidanyiXiadeYouhuoshu/js/epub.min.map
BidanyiXiadeYouhuoshu/js/hooks.min.js
BidanyiXiadeYouhuoshu/js/hooks.min.map
BidanyiXiadeYouhuoshu/js/reader.js
BidanyiXiadeYouhuoshu/js/reader.js.map
BidanyiXiadeYouhuoshu/js/reader.min.js
BidanyiXiadeYouhuoshu/js/reader.min.map
BidanyiXiadeYouhuoshu/js/hooks/__init__.py
BidanyiXiadeYouhuoshu/js/hooks/extensions/__init__.py
BidanyiXiadeYouhuoshu/js/hooks/extensions/highlight.js
BidanyiXiadeYouhuoshu/js/libs/__init__.py
BidanyiXiadeYouhuoshu/js/libs/jquery.min.js
BidanyiXiadeYouhuoshu/js/libs/localforage.min.js
BidanyiXiadeYouhuoshu/js/libs/screenfull.js
BidanyiXiadeYouhuoshu/js/libs/screenfull.min.js
BidanyiXiadeYouhuoshu/js/libs/zip.min.js
BidanyiXiadeYouhuoshu/js/plugins/__init__.py
bidanyi_xiade_youhuoshu-2022.10.11.0.dist-info/METADATA
bidanyi_xiade_youhuoshu-2022.10.11.0.dist-info/WHEEL
bidanyi_xiade_youhuoshu-2022.10.11.0.dist-info/entry_points.txt
bidanyi_xiade_youhuoshu-2022.10.11.0.dist-info/top_level.txt
bidanyi_xiade_youhuoshu-2022.10.11.0.dist-info/RECORD
